scaffold.py
llm_agent_scaffolder-0.1.1.dist-info/licenses/LICENSE
llm_agent_scaffolder-0.1.1.dist-info/METADATA
llm_agent_scaffolder-0.1.1.dist-info/WHEEL
llm_agent_scaffolder-0.1.1.dist-info/entry_points.txt
llm_agent_scaffolder-0.1.1.dist-info/top_level.txt
llm_agent_scaffolder-0.1.1.dist-info/RECORD
