Metadata-Version: 2.4
Name: llm-agent-scaffolder
Version: 0.1.1
Summary: A scaffolding tool to quickly generate a boilerplate for a custom LLM Agent Framework.
Author-email: Uday Valera <udayvalera@gmail.com>
License: MIT License
Project-URL: Homepage, https://github.com/udayvalera/llm-agent-scaffolder
Project-URL: Bug Tracker, https://github.com/udayvalera/llm-agent-scaffolder/issues
Keywords: llm,agent,framework,scaffolding,boilerplate,gemini
Classifier: Programming Language :: Python :: 3
Classifier: License :: OSI Approved :: MIT License
Classifier: Operating System :: OS Independent
Classifier: Topic :: Software Development :: Code Generators
Classifier: Topic :: Scientific/Engineering :: Artificial Intelligence
Requires-Python: >=3.8
License-File: LICENSE
Dynamic: license-file
